azurex/__init__.py
azurex/cosmos/__init__.py
azurex/cosmos/cosmos_crud_service.py
azurex-0.0.2a1.dist-info/licenses/LICENSE
azurex-0.0.2a1.dist-info/METADATA
azurex-0.0.2a1.dist-info/WHEEL
azurex-0.0.2a1.dist-info/top_level.txt
azurex-0.0.2a1.dist-info/RECORD
