Metadata-Version: 2.4
Name: AzureX
Version: 0.0.2a1
Summary: AzureX is a Python library that provides a simple and efficient way to interact with Azure services.
Author-email: Raval Sahil <ravalsahil1311@gmail.com>
Maintainer-email: Raval Sahil <ravalsahil1311@gmail.com>
License-Expression: MIT
Project-URL: Homepage, https://github.com/VectorVerse/AzureX
Project-URL: Issues, https://github.com/VectorVerse/AzureX/issues
Classifier: Programming Language :: Python :: 3
Classifier: Operating System :: OS Independent
Requires-Python: >=3.11
License-File: LICENSE
Requires-Dist: azure-cosmos>=4.9.0
Requires-Dist: python-dotenv>=1.1.0
Dynamic: license-file
